hicpnewman/__init__.py
hicpnewman/config_manager.py
hicpnewman/hicpnewman_argparser.py
hicpnewman/hicpnewman_commands.py
hicpnewman/hicpnewman_helpers.py
hicpnewman/config/config.json
hicpnewman/config/config_backup.json
hicpnewman/config/config_default.json
hicpnewman/templates/aggregated/htmlreqres.hbs
hicpnewman/templates/aggregated/template-default-colored.hbs
hicpnewman/templates/aggregated/template-default.hbs
hicpnewman/templates/full/htmlreqres.hbs
hicpnewman/templates/full/template-default-colored.hbs
hicpnewman/templates/full/template-default.hbs
hicpnewman/templates/original/htmlreqres.hbs
hicpnewman/templates/original/template-default-colored.hbs
hicpnewman/templates/original/template-default.hbs
hicpnewman-1.0.5.dist-info/LICENSE.txt
hicpnewman-1.0.5.dist-info/METADATA
hicpnewman-1.0.5.dist-info/WHEEL
hicpnewman-1.0.5.dist-info/entry_points.txt
hicpnewman-1.0.5.dist-info/top_level.txt
hicpnewman-1.0.5.dist-info/RECORD
